Changelog.md
MANIFEST.in
README.md
VERSION
setup.py
isdc_geoavalanche.egg-info/PKG-INFO
isdc_geoavalanche.egg-info/SOURCES.txt
isdc_geoavalanche.egg-info/dependency_links.txt
isdc_geoavalanche.egg-info/not-zip-safe
isdc_geoavalanche.egg-info/top_level.txt
isdc_geoavalanches/__init__.py
isdc_geoavalanches/static/isdc_geoavalanches/js/addavalanches.js
isdc_geoavalanches/static/isdc_geoavalanches/js/avalanches.min.js