Metadata-Version: 1.0
Name: isdc-geoavalanche
Version: 1.0.0
Summary: avalanches module
Home-page: UNKNOWN
Author: iMMAP
Author-email: asdc@immap.org
License: iMMAP
Platform: UNKNOWN
